gitpulse/__init__.py
gitpulse/main.py
gitpulse_cli-0.1.0.dist-info/licenses/LICENSE
gitpulse_cli-0.1.0.dist-info/METADATA
gitpulse_cli-0.1.0.dist-info/WHEEL
gitpulse_cli-0.1.0.dist-info/entry_points.txt
gitpulse_cli-0.1.0.dist-info/top_level.txt
gitpulse_cli-0.1.0.dist-info/RECORD
