Metadata-Version: 2.4
Name: gitpulse-cli
Version: 0.1.0
Summary: A lightweight CLI tool that reports Git pull events to a GitPulse server.
Author-email: Tayo Adepetu <youremail@example.com>
License: MIT
Project-URL: Homepage, https://github.com/yourusername/gitpulse-cli
Project-URL: Repository, https://github.com/yourusername/gitpulse-cli
Project-URL: Issues, https://github.com/yourusername/gitpulse-cli/issues
Keywords: git,cli,hooks,automation,laravel,gitpulse
Classifier: Programming Language :: Python :: 3
Classifier: License :: OSI Approved :: MIT License
Classifier: Operating System :: OS Independent
Requires-Python: >=3.7
License-File: LICENSE
Requires-Dist: requests>=2.25.0
Dynamic: license-file
